{"stats":{"minecraft:killed":{"minecraft:zombie":1},"minecraft:custom":{"minecraft:open_chest":6,"minecraft:time_since_rest":44056,"minecraft:damage_dealt":100,"minecraft:damage_taken":290,"minecraft:crouch_one_cm":85,"minecraft:leave_game":4,"minecraft:play_time":51179,"minecraft:sprint_one_cm":125882,"minecraft:time_since_death":44022,"minecraft:walk_one_cm":223763,"minecraft:deaths":1,"minecraft:sneak_time":34,"minecraft:total_world_time":51179,"minecraft:climb_one_cm":1712,"minecraft:mob_kills":1,"minecraft:fall_one_cm":31727,"minecraft:fly_one_cm":217821,"minecraft:jump":1191},"minecraft:killed_by":{"minecraft:skeleton":1},"minecraft:used":{"minecraft:beetroot":11,"createcafe:oreo":8}},"DataVersion":3120}